gdtree/__init__.py
gdtree/__main__.py
gdtree/app.py
gdtree/end_state_history.py
gdtree/filestring.py
gdtree/traverse.py
gdtree/utils.py
gdtree-0.0.1.dist-info/LICENSE
gdtree-0.0.1.dist-info/METADATA
gdtree-0.0.1.dist-info/WHEEL
gdtree-0.0.1.dist-info/entry_points.txt
gdtree-0.0.1.dist-info/top_level.txt
gdtree-0.0.1.dist-info/RECORD
