Metadata-Version: 2.1
Name: gdtree
Version: 0.0.1
Summary: Generates a pretty-printed directory tree
Home-page: https://github.com/skunichetty/gdtree
Author: Sachchit Kunichetty
Author-email: skunich@umich.edu
License: MIT License
Platform: UNKNOWN
Classifier: Programming Language :: Python :: 3
Classifier: Programming Language :: Python :: 3.8
Classifier: License :: OSI Approved :: MIT License
Classifier: Operating System :: OS Independent
Requires-Python: >=3.8
License-File: LICENSE
Requires-Dist: colorama
